MyEasyTools2025/__init__.py
MyEasyTools2025/calc.py
MyEasyTools2025/helper.py
myeasytools2025-0.0.2.dist-info/licenses/LICENSE
myeasytools2025-0.0.2.dist-info/METADATA
myeasytools2025-0.0.2.dist-info/WHEEL
myeasytools2025-0.0.2.dist-info/top_level.txt
myeasytools2025-0.0.2.dist-info/RECORD
