Metadata-Version: 2.4
Name: MyEasyTools2025
Version: 0.0.2
Summary: This is my easy tools
Author-email: ahmed <ahmed_tt6hs@example.com>
License: MIT License
License-File: LICENSE
Dynamic: license-file
